LICENSE
MANIFEST.in
README.md
setup.py
keras_bcr/__init__.py
keras_bcr/bcr.py
keras_bcr.egg-info/PKG-INFO
keras_bcr.egg-info/SOURCES.txt
keras_bcr.egg-info/dependency_links.txt
keras_bcr.egg-info/requires.txt
keras_bcr.egg-info/top_level.txt
keras_bcr.egg-info/zip-safe
test/__init__.py
test/test_bcr.py