Metadata-Version: 2.4
Name: keras-bcr
Version: 0.3.1
Summary: Batch Correlation Regularizer for TF2/Keras
Home-page: http://github.com/ulf1/keras-bcr
Author: Ulf Hamster
Author-email: 554c46@gmail.com
License: Apache License 2.0
Requires-Python: >=3.7
License-File: LICENSE
Requires-Dist: tensorflow<3,>=2.4.0
Dynamic: author
Dynamic: author-email
Dynamic: description
Dynamic: description-content-type
Dynamic: home-page
Dynamic: license
Dynamic: license-file
Dynamic: requires-dist
Dynamic: requires-python
Dynamic: summary
